multidl/__init__.py
multidl/__main__.py
multidl/config.py
multidl/core.py
multidl/term.py
multidl/utils.py
multidl/services/helpers.py
multidl/services/spotify.py
multidl/services/yt.py
multidl-2.1.3.dist-info/METADATA
multidl-2.1.3.dist-info/WHEEL
multidl-2.1.3.dist-info/entry_points.txt
multidl-2.1.3.dist-info/licenses/LICENSE
multidl-2.1.3.dist-info/RECORD
