Metadata-Version: 2.4
Name: multidl
Version: 2.1.3
Summary: A cli tool for downloading media from various platforms.
Project-URL: Homepage, https://github.com/swayam25/Multi-DL
Project-URL: GitHub, https://github.com/swayam25/Multi-DL
Author: Swayam
License-Expression: GPL-3.0
License-File: LICENSE
Requires-Python: >=3.13
Requires-Dist: aiohttp>=3.11.18
Requires-Dist: click>=8.2.0
Requires-Dist: ffmpeg>=1.4
Requires-Dist: mutagen>=1.47.0
Requires-Dist: platformdirs>=4.3.8
Requires-Dist: pyfiglet>=1.0.2
Requires-Dist: rich>=14.0.0
Requires-Dist: spotipy>=2.25.1
Requires-Dist: toml>=0.10.2
Requires-Dist: trogon>=0.6.0
Requires-Dist: typer>=0.15.3
Requires-Dist: yt-dlp>=2025.11.12
